<corpus>
  <file name="ddr1929mip">ddr1929mip_mefaits-instruction-publique.xml</file>
  <file name="ddr1932paysan">ddr1932paysan_paysan-du-danube.xml</file>
  <file name="ddr1934polpers">ddr1934polpers_politique-personne.xml</file>
  <file name="ddr1936pm">ddr1936pm_penser-mains.xml</file>
  <file name="ddr1937jic">ddr1937jic_journal-intellectuel-chomage.xml</file>
  <file name="ddr1938ja">ddr1938ja_journal-allemagne.xml</file>
  <file name="ddr1939ao">ddr1939ao_amour-occident.xml</file>
  <file name="ddr1940mds">ddr1940mds_mission-demission-suisse.xml</file>
  <file name="ddr1942partdia">ddr1942partdia_part-diable.xml</file>
  <file name="ddr1944partdia">ddr1944partdia_part-diable.xml</file>
  <file name="ddr1944persdram">ddr1944persdram_personnes-drame.xml</file>
  <file name="ddr1946jdm">ddr1946jdm_journal-deux-mondes.xml</file>
  <file name="ddr1946lba1">ddr1946lba1_lettre-bombe-atomique-1.xml</file>
  <file name="ddr1946lba2">ddr1946lba2_lettres-bombe-atomique.xml</file>
  <file name="ddr1946polpers">ddr1946polpers_politique-personne.xml</file>
  <file name="ddr1947df">ddr1947df_doctrine-fabuleuse.xml</file>
  <file name="ddr1947va">ddr1947va_vivre-amerique.xml</file>
  <file name="ddr1948ej">ddr1948ej_europe-en-jeu.xml</file>
  <file name="ddr1948sn">ddr1948sn_suite-neuchateloise.xml</file>
  <file name="ddr1950lde">ddr1950lde_lettres-deputes-europeens.xml</file>
  <file name="ddr1953ch">ddr1953ch_confederation-helvetique.xml</file>
  <file name="ddr1956ao">ddr1956ao_amour-occident.xml</file>
  <file name="ddr1957aoh">ddr1957aoh_aventure-occidentale-homme.xml</file>
  <file name="ddr1961ctm">ddr1961ctm_comme-toi-meme-mythes-amour.xml</file>
  <file name="ddr1961vhse">ddr1961vhse_vingt-huit-siecles-europe.xml</file>
  <file name="ddr1962ce">ddr1962ce_chances-europe.xml</file>
  <file name="ddr1968jde">ddr1968jde_journal-epoque.xml</file>
  <file name="ddr1970cde">ddr1970cde_cheminements-esprits.xml</file>
  <file name="ddr1970loe">ddr1970loe_lettre-ouverte-europeens.xml</file>
  <file name="ddr1965shph">ddr1965shph_suisse-histoire-peuple-heureux.xml</file>
  <file name="ddr1970udce">ddr1970udce_un-divers-cite-europenne.xml</file>
  <file name="ddr1972ao">ddr1972ao_amour-occident.xml</file>
  <file name="ddr1972mip">ddr1972mip_mefaits-instruction-publique.xml</file>
  <file name="ddr1972pm">ddr1972pm_penser-mains.xml</file>
  <file name="ddr1977aena">ddr1977aena_avenir-est-notre-affaire.xml</file>
  <file name="ddr1979rpe">ddr1979rpe_rapport-peuple-europeen.xml</file>
  <file name="ddr1982partdia">ddr1982partdia_part-diable.xml</file>
  <file name="ddr1982paysan">ddr1982paysan_paysan-du-danube.xml</file>
</corpus>
